{
  "name": "Batter",
  "description": "A turret that shoots giant drops of water that knock back enemies.",
  "size": 2,
  "range": 200,
  "reloadTime": 60,
  "shootSound": "artillery",
  "shootCone": 360,
  "inaccuracy": 1,
  "ammoTypes": {
    "water": {
      "type": "LiquidBulletType",
      "damage": 20,
      "knockback": 75,
      "lifetime": 57,
      "pierce": true,
      "pierceCap": 25,
      "liquid": "water",
      "status": "freezing",
      "statusDuration": 20
    }
  },
  "rotateSpeed": 200,
  "targetAir": false,
  "targetGround": true,
  "recoilAmount": 1,
  "requirements": [
    {
      "item": "copper",
      "amount": 75
    },
    {
      "item": "silicon",
      "amount": 50
    },
    {
      "item": "graphite",
      "amount": 50
    }
  ],
  "category": "turret",
  "type": "LiquidTurret",
  "health": 420,
  "research": "wet-gattling"
}

  
