{
  "type": "pointDefenseTurret",
  "name": "Fragment",
  "description": "A better version of the Segment. Fires faster and does more damage to bullets. Can still not target lasers.",
  "size": 3,
  "health": 410,
  "range": 236,
  "reload": 3,
  "hasPower": true,
  "shootLength": 14,
  "bulletDamage": 32,
  "consumes": {
    "liquid": {
      "liquid": "living-steel-liquid",
      "amount": 0.1,
      "booster": true,
      "optional": true,
    }
  },
  "liquidBoostIntensity": 1.8,
  "reloadTime": 10,
  "consumes": {
    "power": 10,
    "liquid": {
      "liquid": "cryofluid",
      "amount": 0.03,
      "booster": true,
      "optional": true
    }
  },
  "liquidBoostIntensity": 1.6,
  "requirements": [
    {
      "item": "thorium",
      "amount": 120
    },
    {
      "item": "silicon",
      "amount": 260
    },
    {
      "item": "phase-fabric",
      "amount": 80
    }
  ],
  "category": "turret",
  "research": "segment"
}
