{
  "type": "PointDefenseTurret",
  "name": "Fragment",
  "description": "A better version of the Segment. Fires faster and does more damage to bullets. Can still not target lasers.",
  "size": 3,
  "health": 410,
  "range": 236,
  "reload": 4,
  "hasPower": true,
  "shootLength": 14,
  "bulletDamage": 45,
  "consumes": {
    "power": 10
  },
  "requirements": [
    {"item": "copper", "amount": 200},
    {"item": "lead", "amount": 180},
    {"item": "silicon", "amount": 180},
    {"item": "thorium", "amount": 200},
    {"item": "phase-fabric", "amount": 100}
  ],
  "category": "turret",
  "research": "cavalry"
}
