{
  "type": "flying",
  "name": "Tentacle",
  "description": "Heavy damage sniper drone. Has this name because of the tentacle-like shielding on it's back.",
  "drag": 0.15,
  "speed": 0.8,
  "research": "mod-gate-units",
  "maxVelocity": 0.68,
  "mass": 10,
  "commandLimit": 10,
  "hitsize": 45,
  "health": 10000,
  "flying": true,
  "rotateWeapon": true,
  "engineOffset": 26,
  "engineSize": 5.5,
  "rotatespeed": 0.06,
  "baseRotateSpeed": 0.05,
  "weapons": [
    {
      "name": "nothing",
      "range": 200,
      "x": 0,
      "y": -2,
      "reload": 250,
      "shootSound": "laser",
      "bullet": {
        "type": "LaserBulletType",
        "speed": 20,
        "length": 20,
        "damage": 100,
        "range": 200,
        "collides": true,
        "collidesGround": true,
        "collidesAir": true,
        "collidesBlocks": true,
        "lifetime": 300,
        "pierce": true,
        "fragBullets": 24,
        "fragBullet": {
         "type": "LaserBulletType",
          "speed": 0,
          "shootCone": 360,
          "inaccuracy": 360,
          "lifetime": 200,
          "damage": 100,
          "pierce": true
        }
      }
    }
  ]
}
